[
  {
    "title": "Quiz Regulars",
    "displayText": "25-35 quiz regulars every week (up from 20)",
    "value": "25-35",
    "category": "attendance",
    "timeframe": "weekly",
    "location": "The Anchor",
    "order": 1,
    "isActive": true
  },
  {
    "title": "Food GP Improvement",
    "displayText": "Food GP improved from 58% to 71%",
    "value": "71%",
    "category": "efficiency",
    "timeframe": "current",
    "location": "The Anchor",
    "order": 2,
    "isActive": true
  },
  {
    "title": "Social Media Views",
    "displayText": "60,000-70,000 monthly social media views",
    "value": "60-70k",
    "category": "engagement",
    "timeframe": "monthly",
    "location": "The Anchor",
    "order": 3,
    "isActive": true
  },
  {
    "title": "Customer Database",
    "displayText": "300 opted-in contacts (quality over quantity)",
    "value": "300",
    "category": "database",
    "timeframe": "current",
    "location": "The Anchor",
    "order": 4,
    "isActive": true
  },
  {
    "title": "Value Added",
    "displayText": "£75,000-£100,000 value added to business",
    "value": "£75-100k",
    "category": "value",
    "timeframe": "total",
    "location": "The Anchor",
    "order": 5,
    "isActive": true
  },
  {
    "title": "Sunday Lunch Waste",
    "displayText": "£250 weekly savings on Sunday lunch waste",
    "value": "£250",
    "category": "savings",
    "timeframe": "weekly",
    "location": "The Anchor",
    "order": 6,
    "isActive": true
  },
  {
    "title": "Tasting Night Retention",
    "displayText": "85% retention rate at tasting nights",
    "value": "85%",
    "category": "retention",
    "timeframe": "current",
    "location": "The Anchor",
    "order": 7,
    "isActive": true
  },
  {
    "title": "Time Saved Weekly",
    "displayText": "25 hours saved weekly using AI systems",
    "value": "25 hours",
    "category": "efficiency",
    "timeframe": "weekly",
    "location": "The Anchor",
    "order": 8,
    "isActive": true
  }
]
